LICENSE
README.md
setup.py
PTGB.egg-info/PKG-INFO
PTGB.egg-info/SOURCES.txt
PTGB.egg-info/dependency_links.txt
PTGB.egg-info/requires.txt
PTGB.egg-info/top_level.txt
telegram/__init__.py
telegram/telegram.py
tests/__init__.py
tests/test.py