Metadata-Version: 2.1
Name: PTGB
Version: 0.0.1
Summary: A package for sending Telegram messages
Home-page: https://github.com/kalanakt/PTGB
Author: kalanakt
Author-email: e19198@eng.pdn.ac.lk
Keywords: telegram api
Classifier: Programming Language :: Python :: 3
Classifier: License :: OSI Approved :: MIT License
Classifier: Operating System :: OS Independent
License-File: LICENSE
